supermann/__init__.py
supermann/cli.py
supermann/core.py
supermann/signals.py
supermann/supervisor.py
supermann/utils.py
supermann/metrics/__init__.py
supermann/metrics/process.py
supermann/metrics/system.py
supermann-3.2.0.dist-info/DESCRIPTION.rst
supermann-3.2.0.dist-info/METADATA
supermann-3.2.0.dist-info/RECORD
supermann-3.2.0.dist-info/WHEEL
supermann-3.2.0.dist-info/entry_points.txt
supermann-3.2.0.dist-info/metadata.json
supermann-3.2.0.dist-info/top_level.txt
