Metadata-Version: 2.0
Name: supermann
Version: 3.2.0
Summary: A Supervisor event listener for Riemann
Home-page: https://github.com/borntyping/supermann
Author: Sam Clements
Author-email: sam.clements@datasift.com
License: MIT
Platform: UNKNOWN
Classifier: Development Status :: 4 - Beta
Classifier: Environment :: No Input/Output (Daemon)
Classifier: License :: OSI Approved
Classifier: License :: OSI Approved :: MIT License
Classifier: Operating System :: Unix
Classifier: Programming Language :: Python
Classifier: Programming Language :: Python :: 2
Classifier: Programming Language :: Python :: 2.6
Classifier: Programming Language :: Python :: 2.7
Classifier: Topic :: System :: Logging
Classifier: Topic :: System :: Monitoring
Classifier: Topic :: System :: Networking
Classifier: Topic :: System :: Systems Administration
Requires-Dist: blinker (>=1.1)
Requires-Dist: click (>=6.6)
Requires-Dist: psutil (>=4.3.0)
Requires-Dist: riemann-client (>=6.3.0)
Requires-Dist: supervisor (<4.0,>=3.0)
